AUTHORS
ChangeLog
INSTALL.md
LICENSE
README.md
TODO.ru
docker_file.md
requirements.txt
setup.cfg
setup.py
configs-examples/ceph_fuel.yaml
configs-examples/ceph_raw.yaml
configs-examples/db_raw.yaml
configs-examples/default.yaml
configs-examples/hdd.yaml
configs-examples/local_ceph.yaml
fio_binaries/fio_trusty_x86_64.bz2
report_templates/base.html
report_templates/report_all.html
report_templates/report_ceph.html
report_templates/report_cinder_iscsi.html
report_templates/report_hdd.html
report_templates/report_iops_vs_lat.html
report_templates/report_linearity.html
scripts/__init__.py
scripts/assumptions_check.py
scripts/build_fio_ubuntu.sh
scripts/config.sh
scripts/connector.py
scripts/data.py
scripts/data2.py
scripts/data_extractor.py
scripts/data_generator.py
scripts/disk_io_pp.py
scripts/gen_load.sh
scripts/generate_load.py
scripts/grafana.py
scripts/grafana_template.js
scripts/hdd.fio
scripts/influx_exporter.py
scripts/koder.js
scripts/prepare.sh
scripts/qcow2_vdb.txt
scripts/qcow2_vm.txt
scripts/qcow_compute.txt
scripts/raw_vdb.txt
scripts/raw_vm.txt
scripts/receiver.py
scripts/run.sh
scripts/run_all_tests.sh
scripts/run_test.sh
scripts/run_vm.sh
scripts/show_disk_delta.py
scripts/single_node_test_complete.sh
scripts/single_node_test_short.sh
scripts/tests.yaml
scripts/webui.py
scripts/fio_tests_configs/1.cfg
scripts/fio_tests_configs/2.cfg
scripts/fio_tests_configs/io_task.cfg
scripts/fio_tests_configs/io_task_test.cfg
scripts/postprocessing/__init__.py
scripts/postprocessing/bottleneck.py
scripts/postprocessing/io_py_result_processor.py
scripts/postprocessing/stat.py
scripts/storage/__init__.py
scripts/storage/data_processing.py
scripts/storage/db_manage.py
scripts/storage/models.py
scripts/storage/storage_api.py
tests/__init__.py
tests/fake_run_test.py
tests/test_agent.py
tests/test_executors.py
wally/__init__.py
wally/__main__.py
wally/config.py
wally/fuel_rest_api.py
wally/hw_info.py
wally/keystone.py
wally/main.py
wally/meta_info.py
wally/pretty_yaml.py
wally.egg-info/PKG-INFO
wally.egg-info/SOURCES.txt
wally.egg-info/dependency_links.txt
wally.egg-info/entry_points.txt
wally.egg-info/not-zip-safe
wally.egg-info/pbr.json
wally.egg-info/requires.txt
wally.egg-info/top_level.txt
