Metadata-Version: 1.1
Name: wally
Version: 1.0.dev277
Summary: Block storage test tool
Home-page: https://github.com/Mirantis/disk_perf_test_tool
Author: kostiantyn danilov aka koder
Author-email: kdanilov@mirantis.com
License: UNKNOWN
Platform: UNKNOWN
Classifier: Intended Audience :: Developers
Classifier: Intended Audience :: Information Technology
Classifier: License :: OSI Approved :: Apache Software License
Classifier: Operating System :: POSIX :: Linux
Classifier: Programming Language :: Python
Classifier: Programming Language :: Python :: 2
Classifier: Programming Language :: Python :: 2.7
